sinstruments/__init__.py
sinstruments/__main__.py
sinstruments/pytest.py
sinstruments/simulator.py
sinstruments/simulators/__init__.py
sinstruments/simulators/elettra.py
sinstruments-1.5.0.dist-info/LICENSE
sinstruments-1.5.0.dist-info/METADATA
sinstruments-1.5.0.dist-info/WHEEL
sinstruments-1.5.0.dist-info/entry_points.txt
sinstruments-1.5.0.dist-info/top_level.txt
sinstruments-1.5.0.dist-info/RECORD
