Metadata-Version: 2.2
Name: sinstruments
Version: 1.5.0
Summary: A simulator for real hardware which is accessible via TCP, UDP or serial line
Author-email: Tiago Coutinho <coutinhotiago@gmail.com>
Project-URL: Homepage, https://github.com/tiagocoutinho/sinstruments
Keywords: sinstruments
Classifier: Development Status :: 4 - Beta
Classifier: Intended Audience :: Developers
Classifier: License :: OSI Approved :: GNU General Public License v3 (GPLv3)
Classifier: Natural Language :: English
Classifier: Programming Language :: Python :: 3
Classifier: Programming Language :: Python :: 3.7
Classifier: Programming Language :: Python :: 3.8
Classifier: Programming Language :: Python :: 3.9
Classifier: Programming Language :: Python :: 3.10
Classifier: Programming Language :: Python :: 3.11
Classifier: Programming Language :: Python :: 3.12
Classifier: Programming Language :: Python :: 3.13
Requires-Python: >=3.7
License-File: LICENSE
Requires-Dist: click>=7.1
Requires-Dist: gevent
Provides-Extra: yaml
Requires-Dist: PyYAML; extra == "yaml"
Provides-Extra: toml
Requires-Dist: toml; extra == "toml"
Provides-Extra: all
Requires-Dist: PyYAML; extra == "all"
Requires-Dist: toml; extra == "all"
